wellfit/__init__.py
wellfit/__version__.py
wellfit/fit.py
wellfit/model.py
wellfit/planet.py
wellfit/star.py
wellfit/utils.py
wellfit/wellfit.py
wellfit-0.0b1.dist-info/METADATA
wellfit-0.0b1.dist-info/RECORD
wellfit-0.0b1.dist-info/WHEEL
wellfit-0.0b1.dist-info/top_level.txt
