Metadata-Version: 2.1
Name: wellfit
Version: 0.0b1
Summary: A wellfit package to fit wells well.
Home-page: UNKNOWN
Author: Christina Hedges
Author-email: christina.l.hedges@nasa.gov
License: MIT
Platform: UNKNOWN
Classifier: Development Status :: 1 - Planning
Classifier: License :: OSI Approved :: MIT License
Classifier: Operating System :: OS Independent
Classifier: Programming Language :: Python
Classifier: Intended Audience :: Science/Research
Classifier: Topic :: Scientific/Engineering :: Astronomy
Requires-Dist: numpy (>=1.11)
Requires-Dist: astropy (>=1.3)
Requires-Dist: scipy (>=0.19.0)
Requires-Dist: matplotlib (>=1.5.3)
Requires-Dist: tqdm
Requires-Dist: celerite
Requires-Dist: starry
Requires-Dist: pandas
